setup_calpy.py
opticalib/__init__.py
opticalib/__version__.py
opticalib/alignment.py
opticalib/analyzer.py
opticalib/py.typed
opticalib/typings.py
opticalib/core/__init__.py
opticalib/core/exceptions.py
opticalib/core/fitsarray.py
opticalib/core/read_config.py
opticalib/core/root.py
opticalib/core/_configurations/configuration.yaml
opticalib/devices/__init__.py
opticalib/devices/cameras.py
opticalib/devices/deformable_mirrors.py
opticalib/devices/interferometer.py
opticalib/devices/_API/__init__.py
opticalib/devices/_API/alpaoAPI.py
opticalib/devices/_API/base_devices.py
opticalib/devices/_API/i4d.py
opticalib/devices/_API/micAPI.py
opticalib/devices/_API/piAPI.py
opticalib/devices/_API/splattAPI.py
opticalib/dmutils/__init__.py
opticalib/dmutils/actuator_identification_lib.py
opticalib/dmutils/dm_analysis.py
opticalib/dmutils/flattening.py
opticalib/dmutils/iff_acquisition_preparation.py
opticalib/dmutils/iff_module.py
opticalib/dmutils/iff_processing.py
opticalib/dmutils/pupil_calibration.py
opticalib/dmutils/utils.py
opticalib/ground/__init__.py
opticalib/ground/computerec.py
opticalib/ground/geo.py
opticalib/ground/geometry.py
opticalib/ground/logger.py
opticalib/ground/modal_decomposer.py
opticalib/ground/osutils.py
opticalib/ground/roi.py
opticalib/simulator/__init__.py
opticalib/simulator/factory_functions.py
opticalib/simulator/fake_dms.py
opticalib/simulator/fake_interf.py
opticalib/simulator/_API/__init__.py
opticalib/simulator/_API/alpao_conf.yaml
opticalib/simulator/_API/base_fake_adopticadm.py
opticalib/simulator/_API/base_fake_alpao.py
opticalib/simulator/_API/AdOpticaData/dp_cmdmat.fits
opticalib/simulator/_API/AdOpticaData/dp_coords.fits
opticalib/simulator/_API/AdOpticaData/dp_ffwd.fits
opticalib-1.1.0.dist-info/licenses/LICENSE
tests/__init__.py
tests/conftest.py
tests/test_core_exceptions.py
tests/test_core_fits.py
tests/test_core_read_config.py
tests/test_core_root.py
tests/test_dmutils_flattening.py
tests/test_dmutils_iff_acquisition_preparation.py
tests/test_dmutils_iff_module.py
opticalib-1.1.0.dist-info/METADATA
opticalib-1.1.0.dist-info/WHEEL
opticalib-1.1.0.dist-info/entry_points.txt
opticalib-1.1.0.dist-info/top_level.txt
opticalib-1.1.0.dist-info/RECORD
