Metadata-Version: 2.4
Name: opticalib
Version: 1.1.0
Summary: This package is a python interface for laboratory adaptive optics systems, with a focus on the calibration of deformable mirrors (DMs) and the acquisition of wavefront data using interferometers.
Home-page: https://github.com/ArcetriAdaptiveOptics/opticalib
Author: Adaptive Optics Group - INAF - Osservatorio Astrofisico di Arcetri
Author-email: pietro.ferraiuolo@inaf.it
Maintainer: Pietro Ferraiuolo
License: MIT License
Classifier: Programming Language :: Python :: 3
Classifier: License :: OSI Approved :: MIT License
Classifier: Operating System :: Unix
Requires-Python: >=3.10
License-File: LICENSE
Requires-Dist: arte
Requires-Dist: astropy
Requires-Dist: scikit-image
Requires-Dist: scikit-learn
Requires-Dist: vmbpy
Requires-Dist: pipython
Requires-Dist: scipy
Requires-Dist: plico_dm
Requires-Dist: ruamel.yaml
Requires-Dist: Pyro4
Requires-Dist: h5py
Requires-Dist: jdcal
Requires-Dist: tqdm
Requires-Dist: matplotlib
Requires-Dist: xupy
Requires-Dist: numpy
Dynamic: author
Dynamic: author-email
Dynamic: classifier
Dynamic: description
Dynamic: description-content-type
Dynamic: home-page
Dynamic: license
Dynamic: license-file
Dynamic: maintainer
Dynamic: requires-dist
Dynamic: requires-python
Dynamic: summary
